{
  "$schema": "http://json.schemastore.org/vsix-publish",
  "categories": [ "coding" ],
  "identity": {
    "internalName": "RainbowBraces",
    "tags": [ "color", "braces", "brackets" ]
  },
  "assetFiles": [
    {
      "pathOnDisk": "art/screenshot.png",
      "targetPath": "art/screenshot.png"
    },
    {
      "pathOnDisk": "art/options.png",
      "targetPath": "art/options.png"
    },
    {
      "pathOnDisk": "art/options2.png",
      "targetPath": "art/options2.png"
    },
    {
      "pathOnDisk": "art/menu.png",
      "targetPath": "art/menu.png"
    },
    {
      "pathOnDisk": "art/theme-colors.png",
      "targetPath": "art/theme-colors.png"
    },
    {
      "pathOnDisk": "art/vertical-adornments.png",
      "targetPath": "art/vertical-adornments.png"
    },
    {
      "pathOnDisk": "art/vertical-adornments-options.png",
      "targetPath": "art/vertical-adornments-options.png"
    }
  ],
  "overview": "README.md",
  "publisher": "MadsKristensen",
  "repo": "https://github.com/MadsKristensen/RainbowBraces"
}